gitbatch/__init__.py
gitbatch/__main__.py
gitbatch/config.py
gitbatch/gitbatch.py
gitbatch/parallel.py
gitbatch/repos.py
gitbatch/tasks.py
gitbatch-0.0.1.dist-info/LICENSE.txt
gitbatch-0.0.1.dist-info/METADATA
gitbatch-0.0.1.dist-info/WHEEL
gitbatch-0.0.1.dist-info/entry_points.txt
gitbatch-0.0.1.dist-info/top_level.txt
gitbatch-0.0.1.dist-info/RECORD
