Metadata-Version: 2.1
Name: gitbatch
Version: 0.0.1
Summary: Perform Batch Git operations based on Config file
Home-page: https://github.com/igorlg/gitbatch/
Author: Igor Gentil
Author-email: igor@devops.cool
License: UNKNOWN
Platform: UNKNOWN
Requires-Dist: joblib
Requires-Dist: PyYAML
Requires-Dist: termcolor
Requires-Dist: click
